pytorch_bert/__init__.py
pytorch_bert/feature.py
pytorch_bert/modeling.py
pytorch_bert/tokenizer.py
pytorch_bert/weight_converter.py
pytorch_bert-1.0.0a4.dist-info/METADATA
pytorch_bert-1.0.0a4.dist-info/WHEEL
pytorch_bert-1.0.0a4.dist-info/top_level.txt
pytorch_bert-1.0.0a4.dist-info/RECORD
