Metadata-Version: 2.1
Name: pytorch-bert
Version: 1.0.0a4
Summary: bert implementation
Home-page: https://github.com/jeongukjae/pytorch-bert
Author: Jeong Ukjae
Author-email: jeongukjae@gmail.com
License: UNKNOWN
Platform: UNKNOWN
Classifier: Development Status :: 3 - Alpha
Classifier: Topic :: Scientific/Engineering
Classifier: License :: OSI Approved :: MIT License
Classifier: Programming Language :: Python
Classifier: Programming Language :: Python :: 3
Classifier: Programming Language :: Python :: 3.6
Classifier: Programming Language :: Python :: 3.7
Requires-Python: >=3.6, <3.8
Requires-Dist: torch (>=1.3.0)
Provides-Extra: with-tf
Requires-Dist: tensorflow (>=2.0.0) ; extra == 'with-tf'
Requires-Dist: numpy ; extra == 'with-tf'
